odoo/addons/report_qweb_encrypt/README.rst
odoo/addons/report_qweb_encrypt/__init__.py
odoo/addons/report_qweb_encrypt/__manifest__.py
odoo/addons/report_qweb_encrypt/controllers/__init__.py
odoo/addons/report_qweb_encrypt/controllers/main.py
odoo/addons/report_qweb_encrypt/i18n/es.po
odoo/addons/report_qweb_encrypt/i18n/it.po
odoo/addons/report_qweb_encrypt/i18n/report_qweb_encrypt.pot
odoo/addons/report_qweb_encrypt/models/__init__.py
odoo/addons/report_qweb_encrypt/models/ir_actions_report.py
odoo/addons/report_qweb_encrypt/readme/CONTRIBUTORS.md
odoo/addons/report_qweb_encrypt/readme/DESCRIPTION.md
odoo/addons/report_qweb_encrypt/readme/USAGE.md
odoo/addons/report_qweb_encrypt/static/description/icon.png
odoo/addons/report_qweb_encrypt/static/description/index.html
odoo/addons/report_qweb_encrypt/static/src/report/action_manager_report.esm.js
odoo/addons/report_qweb_encrypt/static/src/report/encrypt_dialog.xml
odoo/addons/report_qweb_encrypt/tests/__init__.py
odoo/addons/report_qweb_encrypt/tests/test_report_qweb_encrypt.py
odoo/addons/report_qweb_encrypt/views/ir_actions_report.xml
odoo_addon_report_qweb_encrypt-18.0.1.0.0.5.dist-info/METADATA
odoo_addon_report_qweb_encrypt-18.0.1.0.0.5.dist-info/WHEEL
odoo_addon_report_qweb_encrypt-18.0.1.0.0.5.dist-info/top_level.txt
odoo_addon_report_qweb_encrypt-18.0.1.0.0.5.dist-info/RECORD
