Metadata-Version: 2.1
Name: odoo-addon-report_qweb_encrypt
Version: 18.0.1.0.0.5
Requires-Python: >=3.10
Requires-Dist: odoo==18.0.*
Summary: Allow to encrypt qweb pdfs
Home-page: https://github.com/OCA/reporting-engine
License: AGPL-3
Author: Creu Blanca,Ecosoft,Odoo Community Association (OCA)
Author-email: support@odoo-community.org
Classifier: Programming Language :: Python
Classifier: Framework :: Odoo
Classifier: Framework :: Odoo :: 18.0
Classifier: License :: OSI Approved :: GNU Affero General Public License v3
